<?xml version="1.0" encoding="utf-8" ?>
<dwsync>
<file name="cropsweat.png" server="C:/xampp/htdocs/SportsArrow/" local="131886222880000000" remote="131886222880000000" Dst="0" />
<file name="cropsweat2.png" server="C:/xampp/htdocs/SportsArrow/" local="131886222880000000" remote="131886222880000000" Dst="0" />
<file name="cropsweat3.png" server="C:/xampp/htdocs/SportsArrow/" local="131886222900000000" remote="131886222900000000" Dst="0" />
<file name="bra.png" server="C:/xampp/htdocs/SportsArrow/" local="131886222820000000" remote="131886222820000000" Dst="0" />
<file name="bra2.png" server="C:/xampp/htdocs/SportsArrow/" local="131886222820000000" remote="131886222820000000" Dst="0" />
<file name="bra3.png" server="C:/xampp/htdocs/SportsArrow/" local="131886222840000000" remote="131886222840000000" Dst="0" />
<file name="singlet.png" server="C:/xampp/htdocs/SportsArrow/" local="131886223180000000" remote="131886223180000000" Dst="0" />
<file name="singlet2.png" server="C:/xampp/htdocs/SportsArrow/" local="131886223200000000" remote="131886223200000000" Dst="0" />
<file name="singlet3.png" server="C:/xampp/htdocs/SportsArrow/" local="131886223200000000" remote="131886223200000000" Dst="0" />
<file name="tight.png" server="C:/xampp/htdocs/SportsArrow/" local="131886223280000000" remote="131886223280000000" Dst="0" />
<file name="tight2.png" server="C:/xampp/htdocs/SportsArrow/" local="131886223280000000" remote="131886223280000000" Dst="0" />
<file name="tight3.png" server="C:/xampp/htdocs/SportsArrow/" local="131886223300000000" remote="131886223300000000" Dst="0" />
<file name="trousers.png" server="C:/xampp/htdocs/SportsArrow/" local="131886223340000000" remote="131886223340000000" Dst="0" />
<file name="trousers2.png" server="C:/xampp/htdocs/SportsArrow/" local="131886223340000000" remote="131886223340000000" Dst="0" />
<file name="trousers3.png" server="C:/xampp/htdocs/SportsArrow/" local="131886223360000000" remote="131886223360000000" Dst="0" />
<file name="performance.png" server="C:/xampp/htdocs/SportsArrow/" local="131886757052333304" remote="131886757050000000" Dst="0" />
<file name="performance2.png" server="C:/xampp/htdocs/SportsArrow/" local="131887209084168511" remote="131887209080000000" Dst="0" />
<file name="performance3.png" server="C:/xampp/htdocs/SportsArrow/" local="131886756639862594" remote="131886756630000000" Dst="0" />
<file name="hiking.png" server="C:/xampp/htdocs/SportsArrow/" local="131886240580000000" remote="131886240580000000" Dst="0" />
<file name="hiking2.png" server="C:/xampp/htdocs/SportsArrow/" local="131886240580000000" remote="131886240580000000" Dst="0" />
<file name="hiking3.png" server="C:/xampp/htdocs/SportsArrow/" local="131886757040839832" remote="131886757040000000" Dst="0" />
<file name="bag.png" server="C:/xampp/htdocs/SportsArrow/" local="131878877721249241" remote="131878877720000000" Dst="0" />
<file name="bag2.png" server="C:/xampp/htdocs/SportsArrow/" local="131886757002791584" remote="131886757000000000" Dst="0" />
<file name="bag3.png" server="C:/xampp/htdocs/SportsArrow/" local="131886757011856401" remote="131886757010000000" Dst="0" />
<file name="cap.png" server="C:/xampp/htdocs/SportsArrow/" local="131886222840000000" remote="131886222840000000" Dst="0" />
<file name="cap2.png" server="C:/xampp/htdocs/SportsArrow/" local="131886757029126538" remote="131886757020000000" Dst="0" />
<file name="cap3.png" server="C:/xampp/htdocs/SportsArrow/" local="131886222860000000" remote="131886222860000000" Dst="0" />
<file name="wristband.png" server="C:/xampp/htdocs/SportsArrow/" local="131886756654044469" remote="131886756650000000" Dst="0" />
<file name="wristband2.png" server="C:/xampp/htdocs/SportsArrow/" local="131886756668885987" remote="131886756660000000" Dst="0" />
<file name="wristband3.png" server="C:/xampp/htdocs/SportsArrow/" local="131886756683037907" remote="131886756680000000" Dst="0" />
<file name="socks.png" server="C:/xampp/htdocs/SportsArrow/" local="131886223220000000" remote="131886223220000000" Dst="0" />
<file name="socks2.png" server="C:/xampp/htdocs/SportsArrow/" local="131886223220000000" remote="131886223220000000" Dst="0" />
<file name="socks3.png" server="C:/xampp/htdocs/SportsArrow/" local="131886223240000000" remote="131886223240000000" Dst="0" />
</dwsync>